{
    "textColor":"C6E6F6",
    "backColor":"2F3338",
    "themeColor":"53C9FF",
    "bgColor":"33373D",
    "iconBorderColor":"ffffff",
    "iconColor":"8A929A",
    "topBarColor":"000000",
    "hudColor":"3F444A",
    
    "markColor":"909399",
    "seplineLineColor":"e5e5e5",
    "quoteTextColor":"777777",
    "homeTitleTextColor":"FFFFFF",
    "quoteBarColor":"858281",
    "linkColor":"6FB8E0",
    
    "statusBarIsWhite":"1",
    "navBarColor":"32363C",
    "navTextColor":"000000",
    "drawerColor":"33373D",
    "midDrawerPadColor":"2F3338",
    "drawerSelectedColor":"3F444A",

    
}


